nebis/__init__.py
nebis/sdk.py
nebis-1.0.0.dist-info/LICENSE
nebis-1.0.0.dist-info/METADATA
nebis-1.0.0.dist-info/WHEEL
nebis-1.0.0.dist-info/top_level.txt
nebis-1.0.0.dist-info/RECORD
