Metadata-Version: 2.1
Name: nebis
Version: 1.0.0
Summary: Nebis Python client
Home-page: https://github.com/nebis-db/pynebis
Author: NebisDB
Author-email: nebisdb@gmail.com
Classifier: Programming Language :: Python :: 3
Classifier: License :: OSI Approved :: GNU General Public License v3 (GPLv3)
Classifier: Operating System :: OS Independent
Requires-Python: >=3.7
License-File: LICENSE
Requires-Dist: requests
Requires-Dist: urllib3
